<!--地基应力-->
<groundStress>
    <!--底流式消力池-->
    <attributeGroup name="地基处理" buildAlias="b0001" alias="gs">
        <attribute name="地基应力" unit="Mpa" type="number" alias="gs0001"/>
    </attributeGroup>
    <!--谷坊-->
    <attributeGroup name="地基处理" buildAlias="b0002" alias="gs">
        <attribute name="地基应力" unit="Mpa" type="number" alias="gs0002"/>
    </attributeGroup>
    <!--开敞式水闸-->
    <attributeGroup name="地基处理" buildAlias="b0056" alias="gs">
        <attribute name="地基应力" unit="Mpa" type="number" alias="gs0003"/>
        <attribute name="固结灌浆孔径φ1/深度h1" unit="mm/m" type="number" alias="gs0004"/>
        <attribute name="固结灌浆孔距b1" unit="m" type="number" alias="gs0005"/>
        <attribute name="换基材料/厚度c" unit="" type="text" alias="gs0006"/>
    </attributeGroup>
    <!--圆形蓄水池-->
    <attributeGroup name="地基处理" buildAlias="b0060" alias="gs">
        <attribute name="地基应力" unit="Mpa" type="number" alias="gs0007"/>
        <attribute name="固结灌浆孔径φ1/深度h1" unit="mm/m" type="number" alias="gs0008"/>
        <attribute name="固结灌浆孔距b1" unit="m" type="number" alias="gs0009"/>
        <attribute name="换基材料/厚度c" unit="" type="text" alias="gs0010"/>
    </attributeGroup>
    <!--泉室-->
    <attributeGroup name="地基处理" buildAlias="b0003" alias="gs">
        <attribute name="地基应力" unit="Mpa" type="number" alias="gs0011"/>
    </attributeGroup>
    <!--渡槽-->
    <attributeGroup name="地基处理" buildAlias="b0061" alias="gs">
        <attribute name="地基应力（排架基础）" unit="Mpa" type="number" alias="gs0012"/>
        <attribute name="地基应力（挡土墙）" unit="Mpa" type="number" alias="gs0013"/>
    </attributeGroup>
    <!--大口井-->
    <attributeGroup name="地基处理" buildAlias="b0005" alias="gs">
        <attribute name="渗透系数" unit="" type="number" alias="gs0014"/>
        <attribute name="影响半径" unit="m" type="number" alias="gs0015"/>
    </attributeGroup>
    <!--管井-->
    <attributeGroup name="地基处理" buildAlias="b0062" alias="gs">
        <attribute name="渗透系数" unit="" type="number" alias="gs0016"/>
        <attribute name="影响半径" unit="m" type="number" alias="gs0017"/>
    </attributeGroup>
    <!--跌水-->
    <attributeGroup name="地基处理" buildAlias="b0011" alias="gs">
        <attribute name="地基应力" unit="Mpa" type="number" alias="gs0018"/>
        <attribute name="固结灌浆孔径φ1/深度h1" unit="mm/m" type="number" alias="gs0019"/>
        <attribute name="固结灌浆孔距b1" unit="m" type="number" alias="gs0020"/>
        <attribute name="换基材料/厚度c" unit="" type="select" select="a,b,c,d" alias="gs0021"/>
    </attributeGroup>
    <!--水表井-->
    <attributeGroup name="地基处理" buildAlias="b0064" alias="gs">
        <attribute name="地基应力" unit="Mpa" type="number" alias="gs0022"/>
        <attribute name="换基材料/厚度c" unit="" type="select" select="0.25,0.5,0.75,1,1.5" alias="gs0023"/>
    </attributeGroup>
    <!--曲线式倒虹吸-->
    <attributeGroup name="地基处理" buildAlias="b0065" alias="gs">
        <attribute name="地基应力（排架基础）" unit="Mpa" type="number" alias="gs0024"/>
        <attribute name="地基应力（挡土墙）" unit="Mpa" type="number" alias="gs0025"/>
    </attributeGroup>
    <!--截水廊道-->
    <attributeGroup name="地基处理" buildAlias="b0004" alias="gs">
        <attribute name="地基应力" unit="Mpa" type="number" alias="gs0026"/>
    </attributeGroup>
</groundStress>